usagelogger/__init__.py
usagelogger/_adapter.py
usagelogger/aiohttp.py
usagelogger/base_logger.py
usagelogger/django.py
usagelogger/flask.py
usagelogger/http_logger.py
usagelogger/http_message.py
usagelogger/http_request_impl.py
usagelogger/http_response_impl.py
usagelogger/http_rule.py
usagelogger/http_rules.py
usagelogger/multipart_utils.py
usagelogger/resurface.py
usagelogger/usage_loggers.py
usagelogger/warnings_utils.py
usagelogger-2.2.5.dist-info/LICENSE
usagelogger-2.2.5.dist-info/METADATA
usagelogger-2.2.5.dist-info/NOTICES.md
usagelogger-2.2.5.dist-info/WHEEL
usagelogger-2.2.5.dist-info/top_level.txt
usagelogger-2.2.5.dist-info/RECORD
