Metadata-Version: 2.1
Name: usagelogger
Version: 2.2.5
Summary: Logging usage of Python-based services, with user privacy by design.
Home-page: https://resurface.io
Author: Resurface Labs
Author-email: admin@resurface.io
License: Apache License 2.0
Project-URL: Bug Reports, https://github.com/resurfaceio/logger-python/issues
Project-URL: Source, https://github.com/resurfaceio/logger-python
Keywords: logging resurface
Platform: UNKNOWN
Classifier: Development Status :: 4 - Beta
Classifier: Intended Audience :: System Administrators
Classifier: Topic :: Internet :: Log Analysis
Classifier: License :: OSI Approved :: Apache Software License
Classifier: Programming Language :: Python :: 3
Classifier: Programming Language :: Python :: 3.7
Classifier: Programming Language :: Python :: 3.8
Classifier: Programming Language :: Python :: 3.9
Requires-Python: >=3.7, <4
Requires-Dist: requests (==2.25.1)
